awsreport/__init__.py
awsreport/__main__.py
awsreport/awsresources/__init__.py
awsreport/awsresources/ami.py
awsreport/awsresources/elasticip.py
awsreport/awsresources/iam.py
awsreport/awsresources/igw.py
awsreport/awsresources/s3.py
awsreport/awsresources/securitygroup.py
awsreport/awsresources/volumes.py
awsreport/core/__init__.py
awsreport/core/analyzer.py
awsreport/core/argument_parser.py
awsreport/core/banner.py
awsreport/core/help_msg.py
awsreport/core/log.py
awsreport-3.0.0.dist-info/METADATA
awsreport-3.0.0.dist-info/WHEEL
awsreport-3.0.0.dist-info/entry_points.txt
awsreport-3.0.0.dist-info/top_level.txt
awsreport-3.0.0.dist-info/RECORD
