Metadata-Version: 2.1
Name: awsreport
Version: 3.0.0
Summary: AWSReport is a tool for analyzing amazon resources.
Home-page: https://github.com/bsd0x/awsreport
Author: Gabriel 'bsd0x' Dutra
Author-email: gmdutra.bsd@gmail.com
License: UNKNOWN
Keywords: aws,report,amazon
Platform: UNKNOWN
Classifier: Programming Language :: Python :: 3
Classifier: License :: OSI Approved :: GNU General Public License (GPL)
Classifier: Operating System :: OS Independent
Classifier: Topic :: Communications :: Email
Requires-Dist: boto3
Requires-Dist: colorama
